django_pg8000/__init__.py
django_pg8000/base.py
django_pg8000/client.py
django_pg8000/creation.py
django_pg8000/features.py
django_pg8000/introspection.py
django_pg8000/operations.py
django_pg8000/psycopg_any.py
django_pg8000/schema.py
django_pg8000-0.0.4.dist-info/METADATA
django_pg8000-0.0.4.dist-info/WHEEL
django_pg8000-0.0.4.dist-info/licenses/LICENSE
django_pg8000-0.0.4.dist-info/RECORD
