Metadata-Version: 2.1
Name: django_pg8000
Version: 0.0.4
Summary: A Django database backend for pg8000
Project-URL: Homepage, https://github.com/tlocke/django_pg8000
License: MIT No Attribution
License-File: LICENSE
Keywords: django,pg8000,postgresql
Classifier: Development Status :: 3 - Alpha
Classifier: Intended Audience :: Developers
Classifier: License :: OSI Approved :: MIT No Attribution License (MIT-0)
Classifier: Operating System :: OS Independent
Classifier: Programming Language :: Python
Classifier: Programming Language :: Python :: 3
Classifier: Programming Language :: Python :: 3.8
Classifier: Programming Language :: Python :: 3.9
Classifier: Programming Language :: Python :: 3.10
Classifier: Programming Language :: Python :: 3.11
Classifier: Programming Language :: Python :: Implementation
Classifier: Programming Language :: Python :: Implementation :: CPython
Classifier: Programming Language :: Python :: Implementation :: PyPy
Requires-Python: >=3.8
Requires-Dist: django
Requires-Dist: pg8000
Requires-Dist: python-dateutil
Requires-Dist: pytz
